firestore_schema_migration-0.1.3.dist-info/licenses/LICENSE
firesync/__init__.py
firesync/__main__.py
firesync/cli.py
firesync/config.py
firesync/gcloud.py
firesync/main.py
firesync/normalizers.py
firesync/operations.py
firesync/schema.py
firesync/workspace.py
firesync/commands/__init__.py
firesync/commands/apply.py
firesync/commands/env.py
firesync/commands/init.py
firesync/commands/plan.py
firesync/commands/pull.py
firestore_schema_migration-0.1.3.dist-info/METADATA
firestore_schema_migration-0.1.3.dist-info/WHEEL
firestore_schema_migration-0.1.3.dist-info/entry_points.txt
firestore_schema_migration-0.1.3.dist-info/top_level.txt
firestore_schema_migration-0.1.3.dist-info/RECORD
