Metadata-Version: 2.4
Name: firestore-schema-migration
Version: 0.1.3
Summary: Infrastructure as Code for Google Cloud Firestore
Author: Pavel Ravvich
License: MIT
Project-URL: Homepage, https://github.com/PavelRavvich/firesync
Project-URL: Repository, https://github.com/PavelRavvich/firesync
Classifier: Programming Language :: Python :: 3
Classifier: Programming Language :: Python :: 3.8
Classifier: Programming Language :: Python :: 3.9
Classifier: Programming Language :: Python :: 3.10
Classifier: Programming Language :: Python :: 3.11
Classifier: Programming Language :: Python :: 3.12
Classifier: License :: OSI Approved :: MIT License
Classifier: Operating System :: OS Independent
Requires-Python: >=3.8
License-File: LICENSE
Requires-Dist: PyYAML>=5.1
Dynamic: license-file
